README.md
setup.py
src/thundra_foresight_inst_helpers/__init__.py
src/thundra_foresight_inst_helpers.egg-info/PKG-INFO
src/thundra_foresight_inst_helpers.egg-info/SOURCES.txt
src/thundra_foresight_inst_helpers.egg-info/dependency_links.txt
src/thundra_foresight_inst_helpers.egg-info/requires.txt
src/thundra_foresight_inst_helpers.egg-info/top_level.txt
src/thundra_foresight_inst_helpers/maven/__init__.py
src/thundra_foresight_inst_helpers/maven/instrument.py
src/thundra_foresight_inst_helpers/utils/__init__.py
src/thundra_foresight_inst_helpers/utils/version_check.py