Metadata-Version: 2.1
Name: thundra-foresight-inst-helpers
Version: 0.1.0
Summary: A collection of instrumentation methods for Thundra Foresight
Home-page: https://github.com/thundra-io/thundra-foresight-inst-helpers
Author: Oguzhan Ozdemir
Author-email: oguzhan.ozdemir@thundra.io
License: MIT
Platform: UNKNOWN
Classifier: Development Status :: 5 - Production/Stable
Classifier: Intended Audience :: Developers
Classifier: License :: OSI Approved :: Apache Software License
Classifier: Operating System :: POSIX :: Linux
Classifier: Programming Language :: Python :: 3
Classifier: Programming Language :: Python :: 3.4
Classifier: Programming Language :: Python :: 3.5
